<?xml version="1.0" encoding="UTF-8"?>
<prefab>
  <property name="CopyAirBlocks" value="True" />
  <property name="AllowTopSoilDecorations" value="True" />
  <property name="TraderArea" value="False" />
  <property name="ExcludeDistantPOIMesh" value="False" />
  <property name="ExcludePOICulling" value="False" />
  <property name="DifficultyTier" value="0" />
  <property name="RotationToFaceNorth" value="2" />
  <property name="YOffset" value="-15" />
  <property name="DistantPOIYOffset" value="0" />
  <property name="EditorGroups" value="tier_0, cave, pre_a20" />
  <property name="SleeperVolumeStart" value="0, 1, 0" />
  <property name="SleeperVolumeSize" value="29, 19, 20" />
  <property name="SleeperVolumeGroup" value="GroupBikerBar,1,5" />
  <property name="SleeperVolumeGameStageAdjust" value=",," />
  <property name="SleeperIsLootVolume" value="False" />
  <property name="SleeperIsQuestExclude" value="False" />
  <property name="SleeperVolumeFlags" value="0" />
  <property name="SleeperVolumeGroupId" value="0" />
  <property name="ShowQuestClearCount" value="1" />
  <property name="PrefabSize" value="29, 20, 20" />
  <property name="SleeperVolumeTriggeredBy" value=" " />
  <property name="Tags" value="wilderness" />
  <property name="ThemeTags" value="cpvwild" />
  <property name="ThemeRepeatDistance" value="750" />
  <property name="DuplicateRepeatDistance" value="16000" />
  <property class="Stats">
    <property name="TotalVertices" value="160124" />
    <property name="TotalTriangles" value="132821" />
    <property class="BlockEntities">
      <property name="Vertices" value="151856" />
      <property name="Triangles" value="122959" />
    </property>
    <property class="ChunkMeshes0">
      <property name="Vertices" value="3670" />
      <property name="Triangles" value="2002" />
    </property>
    <property class="ChunkMeshes1">
      <property name="Vertices" value="0" />
      <property name="Triangles" value="0" />
    </property>
    <property class="ChunkMeshes2">
      <property name="Vertices" value="0" />
      <property name="Triangles" value="0" />
    </property>
    <property class="ChunkMeshes3">
      <property name="Vertices" value="0" />
      <property name="Triangles" value="0" />
    </property>
    <property class="ChunkMeshes4">
      <property name="Vertices" value="0" />
      <property name="Triangles" value="0" />
    </property>
    <property class="ChunkMeshes5">
      <property name="Vertices" value="0" />
      <property name="Triangles" value="0" />
    </property>
    <property class="ChunkMeshes6">
      <property name="Vertices" value="4598" />
      <property name="Triangles" value="7860" />
    </property>
  </property>
  <property class="IndexedBlockOffsets">
    <property class="quest_wood_trees">
      <property name="0" value="25, 16, 16" />
    </property>
  </property>
</prefab>